pixel/__init__.py
pixel/cli.py
pixel/deepzoom.py
pixel/import.py
pixel/pixel.py
pixel/backend/__init__.py
pixel/frontend/Tween.js
pixel/frontend/__init__.py
pixel/frontend/index.html
pixel/frontend/input.js
pixel/frontend/openseadragon.js
pixel/frontend/scene.js
pixel/frontend/texture.js
pixel/frontend/three.js
pixel/frontend/tween.js
pixel-0.4.1.dist-info/DESCRIPTION.rst
pixel-0.4.1.dist-info/METADATA
pixel-0.4.1.dist-info/RECORD
pixel-0.4.1.dist-info/WHEEL
pixel-0.4.1.dist-info/entry_points.txt
pixel-0.4.1.dist-info/metadata.json
pixel-0.4.1.dist-info/top_level.txt
